mezzala/__init__.py
mezzala/_nbdev.py
mezzala/adapters.py
mezzala/blocks.py
mezzala/models.py
mezzala/parameters.py
mezzala/weights.py
mezzala-0.0.6.dist-info/LICENSE
mezzala-0.0.6.dist-info/METADATA
mezzala-0.0.6.dist-info/WHEEL
mezzala-0.0.6.dist-info/entry_points.txt
mezzala-0.0.6.dist-info/top_level.txt
mezzala-0.0.6.dist-info/RECORD
